pyxecm/__init__.py
pyxecm/avts.py
pyxecm/coreshare.py
pyxecm/otac.py
pyxecm/otawp.py
pyxecm/otca.py
pyxecm/otcs.py
pyxecm/otds.py
pyxecm/otiv.py
pyxecm/otkd.py
pyxecm/otmm.py
pyxecm/otpd.py
pyxecm/py.typed
pyxecm/helper/__init__.py
pyxecm/helper/assoc.py
pyxecm/helper/data.py
pyxecm/helper/logadapter.py
pyxecm/helper/web.py
pyxecm/helper/xml.py
pyxecm_api/__init__.py
pyxecm_api/__main__.py
pyxecm_api/app.py
pyxecm_api/settings.py
pyxecm_api/auth/__init__.py
pyxecm_api/auth/functions.py
pyxecm_api/auth/models.py
pyxecm_api/auth/router.py
pyxecm_api/common/__init__.py
pyxecm_api/common/functions.py
pyxecm_api/common/metrics.py
pyxecm_api/common/models.py
pyxecm_api/common/router.py
pyxecm_api/terminal/__init__.py
pyxecm_api/terminal/router.py
pyxecm_api/v1_csai/__init__.py
pyxecm_api/v1_csai/models.py
pyxecm_api/v1_csai/router.py
pyxecm_api/v1_maintenance/__init__.py
pyxecm_api/v1_maintenance/functions.py
pyxecm_api/v1_maintenance/models.py
pyxecm_api/v1_maintenance/router.py
pyxecm_api/v1_otcs/__init__.py
pyxecm_api/v1_otcs/functions.py
pyxecm_api/v1_otcs/router.py
pyxecm_api/v1_payload/__init__.py
pyxecm_api/v1_payload/functions.py
pyxecm_api/v1_payload/models.py
pyxecm_api/v1_payload/router.py
pyxecm_customizer/__init__.py
pyxecm_customizer/__main__.py
pyxecm_customizer/browser_automation.py
pyxecm_customizer/customizer.py
pyxecm_customizer/exceptions.py
pyxecm_customizer/guidewire.py
pyxecm_customizer/k8s.py
pyxecm_customizer/log.py
pyxecm_customizer/m365.py
pyxecm_customizer/payload.py
pyxecm_customizer/payload_list.py
pyxecm_customizer/salesforce.py
pyxecm_customizer/sap.py
pyxecm_customizer/servicenow.py
pyxecm_customizer/settings.py
pyxecm_customizer/successfactors.py
pyxecm_customizer/translate.py
pyxecm_maintenance_page/__init__.py
pyxecm_maintenance_page/__main__.py
pyxecm_maintenance_page/app.py
pyxecm_maintenance_page/settings.py
pyxecm_maintenance_page/static/favicon.avif
pyxecm_maintenance_page/templates/maintenance.html
pyxecm-3.2.0.dist-info/METADATA
pyxecm-3.2.0.dist-info/WHEEL
pyxecm-3.2.0.dist-info/entry_points.txt
pyxecm-3.2.0.dist-info/RECORD
