Metadata-Version: 2.4
Name: pyxecm
Version: 3.2.0
Summary: A Python library to interact with Opentext Content Management Rest API
Project-URL: Homepage, https://github.com/opentext/pyxecm
Author-email: Kai Gatzweiler <kgatzweiler@opentext.com>, "Dr. Marc Diefenbruch" <mdiefenb@opentext.com>
Keywords: appworks,archivecenter,contentserver,extendedecm,opentext,otds
Classifier: Development Status :: 4 - Beta
Classifier: Intended Audience :: Developers
Classifier: License :: OSI Approved :: Apache Software License
Classifier: Operating System :: OS Independent
Classifier: Programming Language :: Python :: 3
Classifier: Topic :: Internet :: WWW/HTTP :: Dynamic Content :: Content Management System
Requires-Python: >=3.10
Requires-Dist: lxml>=6.0.0
Requires-Dist: opentelemetry-api>=1.34.1
Requires-Dist: opentelemetry-exporter-otlp>=1.34.1
Requires-Dist: opentelemetry-instrumentation-requests>=0.55b1
Requires-Dist: opentelemetry-instrumentation-threading>=0.55b1
Requires-Dist: opentelemetry-sdk>=1.34.1
Requires-Dist: pandas>=2.3.1
Requires-Dist: requests-toolbelt>=1.0.0
Requires-Dist: requests>=2.32.4
Requires-Dist: suds>=1.2.0
Requires-Dist: websockets>=15.0.1
Requires-Dist: xmltodict>=0.14.2
Provides-Extra: api
Requires-Dist: asyncio>=3.4.3; extra == 'api'
Requires-Dist: fastapi>=0.116.0; extra == 'api'
Requires-Dist: jinja2>=3.1.6; extra == 'api'
Requires-Dist: opentelemetry-api>=1.34.1; extra == 'api'
Requires-Dist: opentelemetry-instrumentation-fastapi>=0.55b1; extra == 'api'
Requires-Dist: opentelemetry-sdk>=1.34.1; extra == 'api'
Requires-Dist: prometheus-fastapi-instrumentator>=7.1.0; extra == 'api'
Requires-Dist: pydantic-settings>=2.10.1; extra == 'api'
Requires-Dist: python-multipart>=0.0.20; extra == 'api'
Requires-Dist: uvicorn>=0.35.0; extra == 'api'
Provides-Extra: customizer
Requires-Dist: kubernetes>=33.1.0; extra == 'customizer'
Requires-Dist: openpyxl>=3.1.5; extra == 'customizer'
Requires-Dist: playwright>=1.53.0; extra == 'customizer'
Requires-Dist: pydantic>=2.11.7; extra == 'customizer'
Requires-Dist: python-hcl2>=7.2.1; extra == 'customizer'
Provides-Extra: magic
Requires-Dist: python-magic; extra == 'magic'
Provides-Extra: sap
Requires-Dist: pyrfc==3.3.1; extra == 'sap'
